bitdefender_msp/__init__.py
bitdefender_msp/client.py
bitdefender_msp/exceptions.py
bitdefender_msp_client-0.1.2.dist-info/License.txt
bitdefender_msp_client-0.1.2.dist-info/METADATA
bitdefender_msp_client-0.1.2.dist-info/WHEEL
bitdefender_msp_client-0.1.2.dist-info/top_level.txt
bitdefender_msp_client-0.1.2.dist-info/RECORD
